comm/ComTimer.py
comm/Packet.py
comm/__init__.py
elio_uart_comm-1.0.dist-info/METADATA
elio_uart_comm-1.0.dist-info/WHEEL
elio_uart_comm-1.0.dist-info/top_level.txt
elio_uart_comm-1.0.dist-info/RECORD
